anonymizers-0.0.2.dist-info/METADATA
anonymizers-0.0.2.dist-info/WHEEL
anonymizers-0.0.2.dist-info/license_files/LICENSE
anonymizers/__init__.py
anonymizers/anonymizers.cpython-39-x86_64-linux-gnu.so
anonymizers-0.0.2.dist-info/RECORD
