Metadata-Version: 2.1
Name: anonymizers
Version: 0.0.2
Classifier: Programming Language :: Rust
Classifier: Programming Language :: Python :: Implementation :: CPython
Classifier: Programming Language :: Python :: Implementation :: PyPy
License-File: LICENSE
Summary: Data anonymization library
License: Apache-2.0
Requires-Python: >=3.7
Project-URL: repository, https://github.com/qooba/anonymize-rs
